gdf.py
gdf-1.0.1.dist-info/LICENSE.md
gdf-1.0.1.dist-info/METADATA
gdf-1.0.1.dist-info/WHEEL
gdf-1.0.1.dist-info/top_level.txt
gdf-1.0.1.dist-info/RECORD
