Metadata-Version: 2.1
Name: gdf
Version: 1.0.1
Summary: Python package to read and write network graphs in GDF (Graph Data Format).
Home-page: https://github.com/nelsonaloysio/gdf
Author: Nelson Aloysio Reis de Almeida Passos
License: MIT
Project-URL: Source, https://github.com/nelsonaloysio/gdf
Project-URL: Tracker, https://github.com/nelsonaloysio/gdf/issues
Keywords: GDF,Graph,Network,NetworkX
Classifier: Development Status :: 5 - Production/Stable
Classifier: Intended Audience :: Developers
Classifier: Intended Audience :: Information Technology
Classifier: License :: OSI Approved :: MIT License
Classifier: Programming Language :: Python :: 3
Classifier: Topic :: Scientific/Engineering :: Information Analysis
Classifier: Topic :: Software Development :: Libraries :: Python Modules
Requires-Python: >=3
License-File: LICENSE.md
Requires-Dist: networkx >=2.3
Requires-Dist: pandas >=0.25.3
